mcp_stdio.py
base/__init__.py
base/base_crawler.py
config/__init__.py
config/base_config.py
config/extension_config.py
config/tag_collection.py
environment/__init__.py
environment/dp_obj.py
environment/query_all_cookies.py
extension/__init__.py
extension/crawler_factory.py
extension/start_crawler.py
extension/cnblogs/__init__.py
extension/cnblogs/client.py
extension/cnblogs/crawler.py
extension/csdn/__init__.py
extension/csdn/client.py
extension/csdn/crawler.py
extension/halo/__init__.py
extension/halo/client.py
extension/halo/crawler.py
extension/juejin/__init__.py
extension/juejin/client.py
extension/juejin/crawler.py
extension/wechat/__init__.py
extension/wechat/client.py
extension/wechat/crawler.py
extension/zhihu/__init__.py
extension/zhihu/client.py
extension/zhihu/crawler.py
iflow_mcp_one_article_submission-0.1.3.dist-info/licenses/LICENSE
utils/__init__.py
utils/content_convert_util.py
utils/decorator_util.py
utils/field_metadata_util.py
utils/httpx_util.py
utils/importlib_util.py
utils/log_util.py
utils/pyperclip_util.py
web/__init__.py
web/app.py
web/llm/__init__.py
web/llm/mcp/__init__.py
web/llm/mcp/submit.py
web/routers/__init__.py
web/routers/browsers.py
web/routers/state.py
web/routers/uploader.py
web/schemas/__init__.py
web/schemas/home.py
web/schemas/response.py
web/schemas/state.py
iflow_mcp_one_article_submission-0.1.3.dist-info/METADATA
iflow_mcp_one_article_submission-0.1.3.dist-info/WHEEL
iflow_mcp_one_article_submission-0.1.3.dist-info/entry_points.txt
iflow_mcp_one_article_submission-0.1.3.dist-info/top_level.txt
iflow_mcp_one_article_submission-0.1.3.dist-info/RECORD
