Metadata-Version: 2.4
Name: iflow-mcp_one-article-submission
Version: 0.1.3
Summary: A multi-platform article publishing web tool.
Requires-Python: >=3.12
License-File: LICENSE
Requires-Dist: dotenv~=0.9.9
Requires-Dist: drissionpage==4.1.0.14
Requires-Dist: fastapi~=0.115.11
Requires-Dist: httpx==0.27.2
Requires-Dist: jinja2>=3.1.6
Requires-Dist: markdown2==2.5.1
Requires-Dist: mcp>=1.11.0
Requires-Dist: openpyxl~=3.1.5
Requires-Dist: psutil~=7.0.0
Requires-Dist: pydantic~=2.8.2
Requires-Dist: pyperclip~=1.9.0
Requires-Dist: pypinyin==0.53.0
Requires-Dist: python-dotenv~=1.0.1
Requires-Dist: python-multipart>=0.0.20
Requires-Dist: requests==2.32.3
Requires-Dist: tenacity~=9.0.0
Requires-Dist: uvicorn~=0.30.6
Requires-Dist: websocket-client~=1.8.0
Dynamic: license-file
